hectiq_config/__init__.py
hectiq_config/config.py
hectiq_config/utils.py
hectiq_config-1.1.0.dist-info/LICENSE
hectiq_config-1.1.0.dist-info/METADATA
hectiq_config-1.1.0.dist-info/WHEEL
hectiq_config-1.1.0.dist-info/top_level.txt
hectiq_config-1.1.0.dist-info/RECORD
