Metadata-Version: 2.1
Name: hectiq-config
Version: 1.1.0
Summary: A simple API to manipulate configuration files
Author-email: Edward Laurence <edwardl@hectiq.ai>, Charles Murphy <cmurphy@hectiq.ai>
Maintainer-email: Edward Laurence <edwardl@hectiq.ai>, Charles Murphy <cmurphy@hectiq.ai>
Project-URL: Repository, https://github.com/HectiqAI/hectiq-config
Requires-Python: >=3.8
License-File: LICENSE
Requires-Dist: pydantic
Requires-Dist: orjson
